{
    "latest": "6.0.5",
    "versions": [
        {
            "version": "6.0.5",
            "preferredShim": "alpine:3.16.1",
            "shims": [
                {
                    "shim": "alpine:3.16.1",
                    "preferredJVM": "al11",
                    "jvms": [
                        {
                            "jvm": "al11",
                            "build": true,
                            "deploy": true,
                            "registries": [
                                "DockerHub",
                                "Artifactory"
                            ]
                        }
                    ]
                }
            ]
        }
    ]
}