{
    "latest": "10.2.2",
    "versions": [
        {
            "version": "10.3.0-Beta",
            "preferredShim": "alpine",
            "shims": [
                {
                    "shim": "alpine",
                    "preferredJVM": "az11",
                    "jvms": [
                        {
                            "jvm": "az11",
                            "build": true,
                            "deploy": true,
                            "registries": [
                                "DockerHub",
                                "Artifactory"
                            ]
                        }
                    ]
                }
            ]
        },
        {
            "version": "10.2.2",
            "preferredShim": "alpine",
            "shims": [
                {
                    "shim": "alpine",
                    "preferredJVM": "az11",
                    "jvms": [
                        {
                            "jvm": "az11",
                            "build": true,
                            "deploy": true,
                            "registries": [
                                "DockerHub",
                                "Artifactory"
                            ]
                        }
                    ]
                }
            ]
        },
        {
            "version": "10.1.5",
            "preferredShim": "alpine",
            "shims": [
                {
                    "shim": "alpine",
                    "preferredJVM": "az11",
                    "jvms": [
                        {
                            "jvm": "az11",
                            "build": true,
                            "deploy": true,
                            "registries": [
                                "DockerHub",
                                "Artifactory"
                            ]
                        }
                    ]
                }
            ]
        }
    ]
}